deform_ext_autocomplete/__init__.py
deform_ext_autocomplete/static/jquery-ui.min.css
deform_ext_autocomplete/static/jquery-ui.min.js
deform_ext_autocomplete/templates/ext_autocomplete_input.pt
deform_ext_autocomplete/templates/readonly/ext_autocomplete_input.pt
deform_ext_autocomplete-1.0.1.dist-info/LICENSE.txt
deform_ext_autocomplete-1.0.1.dist-info/METADATA
deform_ext_autocomplete-1.0.1.dist-info/WHEEL
deform_ext_autocomplete-1.0.1.dist-info/top_level.txt
deform_ext_autocomplete-1.0.1.dist-info/RECORD
